[
  {
    "platform": "instagram",
    "dir": "20260224_day2",
    "timestamp": "2026-02-24T22:15:00",
    "status": "success",
    "url": "https://www.instagram.com/p/DVJGdXik7R3/",
    "media_id": "3839628563730117751_45884164083"
  },
  {
    "platform": "instagram",
    "dir": "20260224_day3",
    "timestamp": "2026-02-24T22:16:00",
    "status": "success",
    "url": "https://www.instagram.com/p/DVJGiBSk331/",
    "media_id": "3839628883436731893_45884164083"
  },
  {
    "platform": "instagram",
    "dir": "20260224_day4",
    "timestamp": "2026-02-24T22:17:00",
    "status": "success",
    "url": "https://www.instagram.com/p/DVJGog_k0OK/",
    "media_id": "3839629329794548618_45884164083"
  },
  {
    "platform": "instagram",
    "dir": "20260224_day5",
    "timestamp": "2026-02-24T22:18:00",
    "status": "error",
    "error": "This user is inactive so they cannot upload."
  },
  {
    "platform": "instagram",
    "dir": "20260224_day5",
    "timestamp": "2026-02-24T22:30:11.698377",
    "retry": true,
    "status": "error",
    "error": "{\"message\":\"This user is inactive so they cannot upload.\",\"status\":\"fail\"}"
  },
  {
    "platform": "instagram",
    "dir": "20260224_day5",
    "timestamp": "2026-02-25T17:30:13.466456",
    "status": "error",
    "error": "アカウント再開のためのメールを送信することができます。. If you are sure that the password is correct, then change your IP address, because it is added to the blacklist of the Instagram Server"
  },
  {
    "platform": "instagram",
    "dir": "20260224_day5",
    "timestamp": "2026-02-26T17:30:14.976365",
    "status": "error",
    "error": "アカウント再開のためのメールを送信することができます。. If you are sure that the password is correct, then change your IP address, because it is added to the blacklist of the Instagram Server"
  },
  {
    "platform": "instagram",
    "dir": "20260224_day5",
    "timestamp": "2026-02-27T17:30:54.028680",
    "status": "success",
    "media_id": "3841655496823237804_45884164083",
    "code": "DVQTVIFk2ys",
    "url": "https://www.instagram.com/p/DVQTVIFk2ys/"
  },
  {
    "platform": "instagram",
    "dir": "20260225_day2_tue_B01",
    "timestamp": "2026-02-28T09:22:28.410915",
    "status": "dry_run",
    "slides": 6,
    "format": "story"
  },
  {
    "platform": "instagram",
    "dir": "20260225_day2_tue_B01",
    "timestamp": "2026-02-28T09:23:45.720282",
    "status": "success",
    "format": "story"
  },
  {
    "platform": "instagram",
    "dir": "20260225_day6",
    "timestamp": "2026-02-28T20:01:29.890469",
    "status": "success",
    "format": "story"
  },
  {
    "platform": "instagram",
    "dir": "20260226_day3_wed_A04",
    "timestamp": "2026-03-02T17:16:56.444616",
    "status": "success",
    "media_id": "3843822174571042042_45884164083",
    "code": "DVX_-b_E5T6",
    "url": "https://www.instagram.com/p/DVX_-b_E5T6/",
    "format": "carousel"
  },
  {
    "platform": "instagram",
    "dir": "20260227_day4_thu_B02",
    "timestamp": "2026-03-03T12:08:45.297726",
    "status": "success",
    "media_id": "3844391731223885600_45884164083",
    "code": "DVaBek9DHcg",
    "url": "https://www.instagram.com/p/DVaBek9DHcg/",
    "format": "reel"
  },
  {
    "platform": "instagram",
    "dir": "20260228_day5_fri_A05",
    "timestamp": "2026-03-03T21:40:52.722812",
    "status": "dry_run",
    "slides": 5,
    "format": "reel"
  },
  {
    "platform": "instagram",
    "dir": "20260228_day5_fri_A05",
    "timestamp": "2026-03-04T15:02:08.449527",
    "status": "dry_run",
    "slides": 5,
    "format": "single"
  },
  {
    "platform": "instagram",
    "dir": "20260228_day5_fri_A05",
    "timestamp": "2026-03-04T21:21:09.108773",
    "status": "success",
    "media_id": "3845394658290237656_45884164083",
    "code": "DVdlhFkkwDY",
    "url": "https://www.instagram.com/p/DVdlhFkkwDY/",
    "format": "single"
  },
  {
    "platform": "instagram",
    "dir": "20260228_day6_sat_C01",
    "timestamp": "2026-03-05T09:24:33.242137",
    "status": "dry_run",
    "slides": 5,
    "format": "carousel"
  },
  {
    "platform": "instagram",
    "dir": "20260228_day6_sat_C01",
    "timestamp": "2026-03-05T09:27:32.398014",
    "status": "success",
    "media_id": "3845760358531979108_45884164083",
    "code": "DVe4qudk9dk",
    "url": "https://www.instagram.com/p/DVe4qudk9dk/",
    "format": "carousel"
  },
  {
    "platform": "instagram",
    "dir": "20260228_day7_sun_T01",
    "timestamp": "2026-03-05T09:33:02.114645",
    "status": "success",
    "media_id": "3845763092312216293_45884164083",
    "code": "DVe5Sgfk9Ll",
    "url": "https://www.instagram.com/p/DVe5Sgfk9Ll/",
    "format": "carousel"
  },
  {
    "platform": "instagram",
    "dir": "20260303_ai_ある_0301_01",
    "timestamp": "2026-03-05T17:21:37.434358",
    "status": "success",
    "media_id": "3845998911543255468_45884164083",
    "code": "DVfu6IREyGs",
    "url": "https://www.instagram.com/p/DVfu6IREyGs/",
    "format": "carousel"
  },
  {
    "platform": "instagram",
    "dir": "20260303_ai_ある_0301_02",
    "timestamp": "2026-03-06T18:02:03.319410",
    "status": "error",
    "error": "No slides found"
  },
  {
    "platform": "instagram",
    "dir": "20260303_ai_ある_0301_02",
    "timestamp": "2026-03-07T20:16:32.727222",
    "status": "error",
    "error": "No slides found"
  },
  {
    "platform": "instagram",
    "dir": "20260303_ai_ある_0301_02",
    "timestamp": "2026-03-09T17:03:09.611197",
    "status": "error",
    "error": "No slides found"
  }
]